chatgpt_commit_assistant/__init__.py
chatgpt_commit_assistant/chatbot.py
chatgpt_commit_assistant/commit_assistant.py
chatgpt_commit_assistant-0.1.dist-info/METADATA
chatgpt_commit_assistant-0.1.dist-info/WHEEL
chatgpt_commit_assistant-0.1.dist-info/entry_points.txt
chatgpt_commit_assistant-0.1.dist-info/top_level.txt
chatgpt_commit_assistant-0.1.dist-info/RECORD
