Metadata-Version: 2.1
Name: chatgpt-commit-assistant
Version: 0.1
Requires-Dist: openai
Requires-Dist: GitPython
